{
    "document_type": "letter",
    "is_cert_naturalization": false,
    "g325a_attributes": {},
    "is_g325a": false,
    "countries": [
        "United States"
    ],
    "years": [
        "1906",
        "1964"
    ],
    "doc_id": "A13995583_0031",
    "afile_number": "A13995583",
    "dev_idx": 4175,
    "pagenumber": 31,
    "url": "https://d1b7k5w7yjwpfg.cloudfront.net/iiif/2/migrants-state_A13995583_0031/full/full/0/default.jpg",
    "is_afile_redacted": false,
    "is_afile_withdrawn": false,
    "ocr_path": "text_ocr/A13995583_0031.txt",
    "cert_naturalization_attributes": {}
}