{
    "document_type": "misc",
    "doc_id": "A34113415_0019",
    "afile_number": "A34113415",
    "dev_idx": 14850,
    "pagenumber": 19,
    "url": "https://d1b7k5w7yjwpfg.cloudfront.net/iiif/2/migrants-state_A34113415_0019/full/full/0/default.jpg",
    "is_afile_redacted": false,
    "is_afile_withdrawn": false,
    "ocr_path": "text_ocr/A34113415_0019.txt",
    "is_g325a": false,
    "is_cert_naturalization": false,
    "g325a_attributes": {},
    "cert_naturalization_attributes": {},
    "years": [],
    "countries": []
}