{
    "document_type": "form",
    "is_cert_naturalization": false,
    "g325a_attributes": {},
    "is_g325a": false,
    "countries": [
        "United States"
    ],
    "years": [
        "1913",
        "1987",
        "2023",
        "1982"
    ],
    "doc_id": "A40040849_redacted_0053",
    "afile_number": "A40040849",
    "dev_idx": 16242,
    "pagenumber": 53,
    "url": "https://d1b7k5w7yjwpfg.cloudfront.net/iiif/2/migrants-state_A40040849_redacted_0053/full/full/0/default.jpg",
    "is_afile_redacted": true,
    "is_afile_withdrawn": false,
    "ocr_path": "text_ocr/A40040849_redacted_0053.txt",
    "cert_naturalization_attributes": {}
}